indo_scraper/__init__.py
indo_scraper/cli.py
indo_scraper/scraper.py
indo_scraper/utils.py
indo_scraper-1.0.0.dist-info/licenses/LICENSE
indo_scraper-1.0.0.dist-info/METADATA
indo_scraper-1.0.0.dist-info/WHEEL
indo_scraper-1.0.0.dist-info/entry_points.txt
indo_scraper-1.0.0.dist-info/top_level.txt
indo_scraper-1.0.0.dist-info/RECORD
