Metadata-Version: 2.4
Name: indo-scraper
Version: 1.0.0
Summary: Library Python untuk scraping website Indonesia dengan mudah
Home-page: https://github.com/adepratama840/indo-scraper
Author: ADE PRATAMA
Author-email: adepratama20071907@gmail.com
Project-URL: Bug Reports, https://github.com/adepratama840/indo-scraper/issues
Project-URL: Source, https://github.com/adepratama840/indo-scraper
Project-URL: Documentation, https://github.com/adepratama840/indo-scraper/wiki
Keywords: scraping,indonesia,web scraping,data extraction,website
Classifier: Development Status :: 4 - Beta
Classifier: Intended Audience :: Developers
Classifier: License :: OSI Approved :: MIT License
Classifier: Operating System :: OS Independent
Classifier: Programming Language :: Python :: 3
Classifier: Programming Language :: Python :: 3.7
Classifier: Programming Language :: Python :: 3.8
Classifier: Programming Language :: Python :: 3.9
Classifier: Programming Language :: Python :: 3.10
Classifier: Programming Language :: Python :: 3.11
Classifier: Topic :: Internet :: WWW/HTTP
Classifier: Topic :: Software Development :: Libraries :: Python Modules
Classifier: Topic :: Text Processing :: General
Requires-Python: >=3.7
License-File: LICENSE
Requires-Dist: requests>=2.25.1
Requires-Dist: beautifulsoup4>=4.9.3
Requires-Dist: lxml>=4.6.3
Dynamic: author
Dynamic: author-email
Dynamic: classifier
Dynamic: description
Dynamic: description-content-type
Dynamic: home-page
Dynamic: keywords
Dynamic: license-file
Dynamic: project-url
Dynamic: requires-dist
Dynamic: requires-python
Dynamic: summary
